codex_sdk/__init__.py
codex_sdk/codex.py
codex_sdk/codex_options.py
codex_sdk/events.py
codex_sdk/exec.py
codex_sdk/items.py
codex_sdk/output_schema_file.py
codex_sdk/py.typed
codex_sdk/thread.py
codex_sdk/thread_options.py
codex_sdk/turn_options.py
codex_sdk/utils.py
python_codex_sdk-0.1.2.dist-info/WHEEL
python_codex_sdk-0.1.2.dist-info/METADATA
python_codex_sdk-0.1.2.dist-info/RECORD
