Metadata-Version: 2.3
Name: python-codex-sdk
Version: 0.1.2
Summary: Python SDK for OpenAI Codex CLI - A port of the official TypeScript SDK
Keywords: codex,openai,cli,sdk,ai,coding-agent
Author: yor-dev
Author-email: yor-dev <52931599+yor-dev@users.noreply.github.com>
License: Apache-2.0
Classifier: Development Status :: 4 - Beta
Classifier: Intended Audience :: Developers
Classifier: License :: OSI Approved :: Apache Software License
Classifier: Programming Language :: Python :: 3
Classifier: Programming Language :: Python :: 3.12
Classifier: Topic :: Software Development :: Libraries :: Python Modules
Classifier: Topic :: Scientific/Engineering :: Artificial Intelligence
Requires-Dist: aiohttp>=3.13.2
Requires-Dist: pydantic>=2.12.4
Requires-Python: >=3.12
Project-URL: Homepage, https://github.com/yor-dev/python-codex-sdk
Project-URL: Repository, https://github.com/yor-dev/python-codex-sdk
